lydata/__init__.py
lydata/_version.py
lydata/accessor.py
lydata/augmentor.py
lydata/loader.py
lydata/querier.py
lydata/schema.py
lydata/types.py
lydata/utils.py
lydata/validator.py
lydata-0.4.0.dist-info/licenses/LICENSE
lydata-0.4.0.dist-info/METADATA
lydata-0.4.0.dist-info/WHEEL
lydata-0.4.0.dist-info/top_level.txt
lydata-0.4.0.dist-info/RECORD
