Metadata-Version: 2.4
Name: lydata
Version: 0.4.0
Summary: Library for handling lymphatic involvement data
Author-email: Roman Ludwig <roman.ludwig@usz.ch>
License: MIT
Project-URL: source, https://github.com/lycosystem/lydata-package
Project-URL: documentation, https://lydata.readthedocs.io
Keywords: data,lymph,involvement
Classifier: Programming Language :: Python :: 3
Requires-Python: >=3.10
License-File: LICENSE
Requires-Dist: numpy
Requires-Dist: pandas
Requires-Dist: pygithub
Requires-Dist: mistletoe
Requires-Dist: pandera
Requires-Dist: pydantic
Requires-Dist: loguru
Requires-Dist: roman
Provides-Extra: docs
Requires-Dist: sphinx; extra == "docs"
Requires-Dist: sphinx-book-theme; extra == "docs"
Requires-Dist: sphinx-autodoc-typehints; extra == "docs"
Requires-Dist: myst-parser[linkify]; extra == "docs"
Provides-Extra: tests
Requires-Dist: pytest; extra == "tests"
Requires-Dist: pytest-cov; extra == "tests"
Requires-Dist: python-dotenv>=1.1.1; extra == "tests"
Provides-Extra: dev
Requires-Dist: pre-commit; extra == "dev"
Requires-Dist: git-cliff; extra == "dev"
Dynamic: license-file
